.packj.yaml
LICENSE
MANIFEST.in
README.md
requirements.txt
setup.py
packj/__init__.py
packj/main.py
packj/options.py
packj.egg-info/PKG-INFO
packj.egg-info/SOURCES.txt
packj.egg-info/dependency_links.txt
packj.egg-info/entry_points.txt
packj.egg-info/requires.txt
packj.egg-info/top_level.txt
packj/audit/__init__.py
packj/audit/main.py
packj/audit/osv.py
packj/audit/package.py
packj/audit/parse_apis.py
packj/audit/parse_composition.py
packj/audit/parse_repo.py
packj/audit/parse_strace.py
packj/audit/pm_util.py
packj/audit/report.py
packj/audit/static_util.py
packj/audit/config/README.md
packj/audit/config/__init__.py
packj/audit/config/astgen_javascript_smt.config
packj/audit/config/astgen_python_smt.config
packj/audit/config/astgen_ruby_smt.config
packj/audit/config/astgen_ruby_smt.config.bin
packj/audit/config/javascript_api/apis2perms.csv
packj/audit/config/python_api/apis2perms.csv
packj/audit/config/rubygems_api/apis2perms.csv
packj/audit/pm_proxy/__init__.py
packj/audit/pm_proxy/npmjs.py
packj/audit/pm_proxy/parse_gemfile.rb
packj/audit/pm_proxy/pm_base.py
packj/audit/pm_proxy/pypi.py
packj/audit/pm_proxy/rubygems.py
packj/audit/proto/__init__.py
packj/audit/proto/python/__init__.py
packj/audit/proto/python/ast_pb2.py
packj/audit/proto/python/info_pb2.py
packj/audit/proto/python/module_pb2.py
packj/audit/proto/ruby/ast_pb.rb
packj/audit/proto/ruby/behavior_pb.rb
packj/audit/proto/ruby/class_sig_pb.rb
packj/audit/proto/ruby/info_pb.rb
packj/audit/proto/ruby/module_pb.rb
packj/audit/static_proxy/__init__.py
packj/audit/static_proxy/astgen.rb
packj/audit/static_proxy/astgen_py.py
packj/audit/static_proxy/astgen_py3.py
packj/audit/static_proxy/js_analyzer.py
packj/audit/static_proxy/py_analyzer.py
packj/audit/static_proxy/ruby_analyzer.py
packj/audit/static_proxy/static_base.py
packj/audit/strace_parser/__init__.py
packj/audit/strace_parser/rules.yaml
packj/audit/strace_parser/strace.py
packj/audit/strace_parser/strace_systime_analyzer.py
packj/audit/strace_parser/strace_utils.py
packj/audit/strace_parser/syscall_parsers.py
packj/audit/strace_parser/syscalls.py
packj/auth/__init__.py
packj/auth/creds.py
packj/auth/main.py
