Metadata-Version: 2.1
Name: packj
Version: 0.14
Summary: Packj flags "risky" open-source packages in your software supply chain
Home-page: https://github.com/ossillate-inc/packj
Author: Ossillate Inc.
Author-email: oss@ossillate.com
License: GNU AGPLv3
Download-URL: https://github.com/ossillate-inc/packj/archive/refs/tags/placeholder.tar.gz
Project-URL: Bug Tracker, https://github.com/ossillate-inc/packj/issues
Keywords: software supply chain,malware,typo-squatting,vulnerability,open-source software,software composition analysis
Platform: UNKNOWN
Classifier: Development Status :: 4 - Beta
Classifier: Intended Audience :: Developers
Classifier: Topic :: Security
Classifier: License :: OSI Approved :: GNU Affero General Public License v3
Classifier: Programming Language :: Python :: 3
Classifier: Programming Language :: Python :: 3.4
Classifier: Programming Language :: Python :: 3.5
Classifier: Programming Language :: Python :: 3.6
Classifier: Programming Language :: Python :: 3.7
Classifier: Programming Language :: Ruby
Requires-Python: >=3.4
License-File: LICENSE
